{"v":5,"entries":{"packages-accordion--docs":{"id":"packages-accordion--docs","title":"Packages/Accordion","name":"Docs","importPath":"./packages/accordion/demo/accordion.mdx","storiesImports":["./packages/accordion/demo/accordion.stories.tsx"],"type":"docs","tags":["dev","test","autodocs","attached-mdx"]},"packages-accordion--uncontrolled":{"type":"story","id":"packages-accordion--uncontrolled","name":"Uncontrolled","title":"Packages/Accordion","importPath":"./packages/accordion/demo/accordion.stories.tsx","componentPath":"./packages/accordion/src/index.ts","tags":["dev","test","autodocs"]},"packages-accordion--controlled":{"type":"story","id":"packages-accordion--controlled","name":"Controlled","title":"Packages/Accordion","importPath":"./packages/accordion/demo/accordion.stories.tsx","componentPath":"./packages/accordion/src/index.ts","tags":["dev","test","autodocs"]},"packages-breadcrumb--docs":{"id":"packages-breadcrumb--docs","title":"Packages/Breadcrumb","name":"Docs","importPath":"./packages/breadcrumb/demo/breadcrumb.mdx","storiesImports":["./packages/breadcrumb/demo/breadcrumb.stories.tsx"],"type":"docs","tags":["dev","test","autodocs","attached-mdx"]},"packages-breadcrumb--breadcrumb":{"type":"story","id":"packages-breadcrumb--breadcrumb","name":"Breadcrumb","title":"Packages/Breadcrumb","importPath":"./packages/breadcrumb/demo/breadcrumb.stories.tsx","componentPath":"./packages/breadcrumb/src/index.ts","tags":["dev","test","autodocs"]},"packages-combobox--docs":{"id":"packages-combobox--docs","title":"Packages/Combobox","name":"Docs","importPath":"./packages/combobox/demo/combobox.mdx","storiesImports":["./packages/combobox/demo/combobox.stories.tsx"],"type":"docs","tags":["dev","test","autodocs","attached-mdx"]},"packages-combobox--uncontrolled":{"type":"story","id":"packages-combobox--uncontrolled","name":"Uncontrolled","title":"Packages/Combobox","importPath":"./packages/combobox/demo/combobox.stories.tsx","componentPath":"./packages/combobox/src/index.ts","tags":["dev","test","autodocs"]},"packages-combobox--controlled":{"type":"story","id":"packages-combobox--controlled","name":"Controlled","title":"Packages/Combobox","importPath":"./packages/combobox/demo/combobox.stories.tsx","componentPath":"./packages/combobox/src/index.ts","tags":["dev","test","autodocs"]},"packages-combobox-patterns--docs":{"id":"packages-combobox-patterns--docs","title":"Packages/Combobox/[patterns]","name":"Docs","importPath":"./packages/combobox/demo/~patterns/patterns.mdx","storiesImports":["./packages/combobox/demo/~patterns/patterns.stories.tsx"],"type":"docs","tags":["dev","test","autodocs","attached-mdx"]},"packages-combobox-patterns--ime":{"type":"story","id":"packages-combobox-patterns--ime","name":"IME","title":"Packages/Combobox/[patterns]","importPath":"./packages/combobox/demo/~patterns/patterns.stories.tsx","tags":["dev","test","autodocs"]},"packages-field--docs":{"id":"packages-field--docs","title":"Packages/Field","name":"Docs","importPath":"./packages/field/demo/field.mdx","storiesImports":["./packages/field/demo/field.stories.tsx"],"type":"docs","tags":["dev","test","autodocs","attached-mdx"]},"packages-field--field":{"type":"story","id":"packages-field--field","name":"Field","title":"Packages/Field","importPath":"./packages/field/demo/field.stories.tsx","componentPath":"./packages/field/src/index.ts","tags":["dev","test","autodocs"]},"packages-focusjail--docs":{"id":"packages-focusjail--docs","title":"Packages/FocusJail","name":"Docs","importPath":"./packages/focusjail/demo/focusjail.mdx","storiesImports":["./packages/focusjail/demo/focusjail.stories.tsx"],"type":"docs","tags":["dev","test","autodocs","attached-mdx"]},"packages-focusjail--focus-jail":{"type":"story","id":"packages-focusjail--focus-jail","name":"FocusJail","title":"Packages/FocusJail","importPath":"./packages/focusjail/demo/focusjail.stories.tsx","tags":["dev","test","autodocs"]},"packages-focusvisible--docs":{"id":"packages-focusvisible--docs","title":"Packages/FocusVisible","name":"Docs","importPath":"./packages/focusvisible/demo/focusvisible.mdx","storiesImports":["./packages/focusvisible/demo/focusvisible.stories.tsx"],"type":"docs","tags":["dev","test","autodocs","attached-mdx"]},"packages-focusvisible--focus-visible":{"type":"story","id":"packages-focusvisible--focus-visible","name":"FocusVisible","title":"Packages/FocusVisible","importPath":"./packages/focusvisible/demo/focusvisible.stories.tsx","componentPath":"./packages/focusvisible/src/index.ts","tags":["dev","test","autodocs"]},"packages-focusvisible-patterns--docs":{"id":"packages-focusvisible-patterns--docs","title":"Packages/FocusVisible/[patterns]","name":"Docs","importPath":"./packages/focusvisible/demo/~patterns/patterns.mdx","storiesImports":["./packages/focusvisible/demo/~patterns/patterns.stories.tsx"],"type":"docs","tags":["dev","test","autodocs","attached-mdx"]},"packages-focusvisible-patterns--selection":{"type":"story","id":"packages-focusvisible-patterns--selection","name":"Selection","title":"Packages/FocusVisible/[patterns]","importPath":"./packages/focusvisible/demo/~patterns/patterns.stories.tsx","tags":["dev","test","autodocs"]},"packages-grid--docs":{"id":"packages-grid--docs","title":"Packages/Grid","name":"Docs","importPath":"./packages/grid/demo/grid.mdx","storiesImports":["./packages/grid/demo/grid.stories.tsx"],"type":"docs","tags":["dev","test","autodocs","attached-mdx"]},"packages-grid--uncontrolled":{"type":"story","id":"packages-grid--uncontrolled","name":"Uncontrolled","title":"Packages/Grid","importPath":"./packages/grid/demo/grid.stories.tsx","componentPath":"./packages/grid/src/index.ts","tags":["dev","test","autodocs"]},"packages-grid--controlled":{"type":"story","id":"packages-grid--controlled","name":"Controlled","title":"Packages/Grid","importPath":"./packages/grid/demo/grid.stories.tsx","componentPath":"./packages/grid/src/index.ts","tags":["dev","test","autodocs"]},"packages-menu--docs":{"id":"packages-menu--docs","title":"Packages/Menu","name":"Docs","importPath":"./packages/menu/demo/menu.mdx","storiesImports":["./packages/menu/demo/menu.stories.tsx"],"type":"docs","tags":["dev","test","autodocs","attached-mdx"]},"packages-menu--uncontrolled":{"type":"story","id":"packages-menu--uncontrolled","name":"Uncontrolled","title":"Packages/Menu","importPath":"./packages/menu/demo/menu.stories.tsx","componentPath":"./packages/menu/src/index.ts","tags":["dev","test","autodocs"]},"packages-menu--controlled":{"type":"story","id":"packages-menu--controlled","name":"Controlled","title":"Packages/Menu","importPath":"./packages/menu/demo/menu.stories.tsx","componentPath":"./packages/menu/src/index.ts","tags":["dev","test","autodocs"]},"packages-menu-patterns--docs":{"id":"packages-menu-patterns--docs","title":"Packages/Menu/[patterns]","name":"Docs","importPath":"./packages/menu/demo/~patterns/patterns.mdx","storiesImports":["./packages/menu/demo/~patterns/patterns.stories.tsx"],"type":"docs","tags":["dev","test","autodocs","attached-mdx"]},"packages-menu-patterns--nested-focus-uncontrolled":{"type":"story","id":"packages-menu-patterns--nested-focus-uncontrolled","name":"Nested focus uncontrolled","title":"Packages/Menu/[patterns]","importPath":"./packages/menu/demo/~patterns/patterns.stories.tsx","tags":["dev","test","autodocs"]},"packages-menu-patterns--nested-focus-controlled":{"type":"story","id":"packages-menu-patterns--nested-focus-controlled","name":"Nested focus controlled","title":"Packages/Menu/[patterns]","importPath":"./packages/menu/demo/~patterns/patterns.stories.tsx","tags":["dev","test","autodocs"]},"packages-modal--docs":{"id":"packages-modal--docs","title":"Packages/Modal","name":"Docs","importPath":"./packages/modal/demo/modal.mdx","storiesImports":["./packages/modal/demo/modal.stories.tsx"],"type":"docs","tags":["dev","test","autodocs","attached-mdx"]},"packages-modal--modal":{"type":"story","id":"packages-modal--modal","name":"Modal","title":"Packages/Modal","importPath":"./packages/modal/demo/modal.stories.tsx","tags":["dev","test","autodocs"]},"packages-schedule--docs":{"id":"packages-schedule--docs","title":"Packages/Schedule","name":"Docs","importPath":"./packages/schedule/demo/schedule.mdx","storiesImports":["./packages/schedule/demo/schedule.stories.tsx"],"type":"docs","tags":["dev","test","autodocs","attached-mdx"]},"packages-schedule--schedule":{"type":"story","id":"packages-schedule--schedule","name":"Schedule","title":"Packages/Schedule","importPath":"./packages/schedule/demo/schedule.stories.tsx","componentPath":"./packages/schedule/src/index.ts","tags":["dev","test","autodocs"]},"packages-scrollregion--docs":{"id":"packages-scrollregion--docs","title":"Packages/ScrollRegion","name":"Docs","importPath":"./packages/scrollregion/demo/scrollregion.mdx","storiesImports":["./packages/scrollregion/demo/scrollregion.stories.tsx"],"type":"docs","tags":["dev","test","autodocs","attached-mdx"]},"packages-scrollregion--scroll-region":{"type":"story","id":"packages-scrollregion--scroll-region","name":"ScrollRegion","title":"Packages/ScrollRegion","importPath":"./packages/scrollregion/demo/scrollregion.stories.tsx","tags":["dev","test","autodocs"]},"packages-selection--docs":{"id":"packages-selection--docs","title":"Packages/Selection","name":"Docs","importPath":"./packages/selection/demo/selection.mdx","storiesImports":["./packages/selection/demo/selection.stories.tsx"],"type":"docs","tags":["dev","test","autodocs","attached-mdx"]},"packages-selection--uncontrolled":{"type":"story","id":"packages-selection--uncontrolled","name":"Uncontrolled","title":"Packages/Selection","importPath":"./packages/selection/demo/selection.stories.tsx","componentPath":"./packages/selection/src/index.ts","tags":["dev","test","autodocs"]},"packages-selection--controlled":{"type":"story","id":"packages-selection--controlled","name":"Controlled","title":"Packages/Selection","importPath":"./packages/selection/demo/selection.stories.tsx","componentPath":"./packages/selection/src/index.ts","tags":["dev","test","autodocs"]},"packages-slider--docs":{"id":"packages-slider--docs","title":"Packages/Slider","name":"Docs","importPath":"./packages/slider/demo/slider.mdx","storiesImports":["./packages/slider/demo/slider.stories.tsx"],"type":"docs","tags":["dev","test","autodocs","attached-mdx"]},"packages-slider--uncontrolled":{"type":"story","id":"packages-slider--uncontrolled","name":"Uncontrolled","title":"Packages/Slider","importPath":"./packages/slider/demo/slider.stories.tsx","tags":["dev","test","autodocs"]},"packages-slider--controlled":{"type":"story","id":"packages-slider--controlled","name":"Controlled","title":"Packages/Slider","importPath":"./packages/slider/demo/slider.stories.tsx","tags":["dev","test","autodocs"]},"packages-splitter--docs":{"id":"packages-splitter--docs","title":"Packages/Splitter","name":"Docs","importPath":"./packages/splitter/demo/splitter.mdx","storiesImports":["./packages/splitter/demo/splitter.stories.tsx"],"type":"docs","tags":["dev","test","autodocs","attached-mdx"]},"packages-splitter--uncontrolled":{"type":"story","id":"packages-splitter--uncontrolled","name":"Uncontrolled","title":"Packages/Splitter","importPath":"./packages/splitter/demo/splitter.stories.tsx","tags":["dev","test","autodocs"]},"packages-splitter--controlled":{"type":"story","id":"packages-splitter--controlled","name":"Controlled","title":"Packages/Splitter","importPath":"./packages/splitter/demo/splitter.stories.tsx","tags":["dev","test","autodocs"]},"packages-tabs--docs":{"id":"packages-tabs--docs","title":"Packages/Tabs","name":"Docs","importPath":"./packages/tabs/demo/tabs.mdx","storiesImports":["./packages/tabs/demo/tabs.stories.tsx"],"type":"docs","tags":["dev","test","autodocs","attached-mdx"]},"packages-tabs--uncontrolled":{"type":"story","id":"packages-tabs--uncontrolled","name":"Uncontrolled","title":"Packages/Tabs","importPath":"./packages/tabs/demo/tabs.stories.tsx","componentPath":"./packages/tabs/src/index.ts","tags":["dev","test","autodocs"]},"packages-tabs--controlled":{"type":"story","id":"packages-tabs--controlled","name":"Controlled","title":"Packages/Tabs","importPath":"./packages/tabs/demo/tabs.stories.tsx","componentPath":"./packages/tabs/src/index.ts","tags":["dev","test","autodocs"]},"packages-tooltip--docs":{"id":"packages-tooltip--docs","title":"Packages/Tooltip","name":"Docs","importPath":"./packages/tooltip/demo/tooltip.mdx","storiesImports":["./packages/tooltip/demo/tooltip.stories.tsx"],"type":"docs","tags":["dev","test","autodocs","attached-mdx"]},"packages-tooltip--tooltip":{"type":"story","id":"packages-tooltip--tooltip","name":"Tooltip","title":"Packages/Tooltip","importPath":"./packages/tooltip/demo/tooltip.stories.tsx","componentPath":"./packages/tooltip/src/index.ts","tags":["dev","test","autodocs"]},"packages-tooltip-patterns--docs":{"id":"packages-tooltip-patterns--docs","title":"Packages/Tooltip/[patterns]","name":"Docs","importPath":"./packages/tooltip/demo/~patterns/patterns.mdx","storiesImports":["./packages/tooltip/demo/~patterns/patterns.stories.tsx"],"type":"docs","tags":["dev","test","autodocs","attached-mdx"]},"packages-tooltip-patterns--focus":{"type":"story","id":"packages-tooltip-patterns--focus","name":"Focus","title":"Packages/Tooltip/[patterns]","importPath":"./packages/tooltip/demo/~patterns/patterns.stories.tsx","tags":["dev","test","autodocs"]}}}